librum/errors.py
librum/files.py
librum/patterns.py
librum/sections.py
librum-0.1.1.dist-info/LICENSE
librum-0.1.1.dist-info/METADATA
librum-0.1.1.dist-info/WHEEL
librum-0.1.1.dist-info/RECORD
